perse/__init__.py
perse/core/__init__.py
perse/core/base.py
perse/core/copy.py
perse/core/dataframe.py
perse/core/df_utilities.py
perse/core/plotting.py
perse/core/sql_operations.py
perse-0.1.9.dist-info/METADATA
perse-0.1.9.dist-info/WHEEL
perse-0.1.9.dist-info/top_level.txt
perse-0.1.9.dist-info/RECORD
