Metadata-Version: 2.1
Name: perse
Version: 0.1.9
Summary: Perse is a unified DataFrame package that combines the best of Pandas, Polars, and DuckDB for efficient data handling, querying, and visualization.
Author-email: Sermet Pekin <Sermet.Pekin@gmail.com>
Project-URL: repository, https://github.com/SermetPekin/perse
Project-URL: documentation, https://perse.readthedocs.io/en/latest/home.html
Project-URL: issue_tracker, https://github.com/SermetPekin/perse/issues
Keywords: dataframe,polars,pandas,duckdb,data-science,data-analysis,SQL,visualization
Requires-Python: >=3.10
Requires-Dist: duckdb>=1.1.3
Requires-Dist: matplotlib>=3.9.2
Requires-Dist: numpy>=2.0.2
Requires-Dist: openpyxl>=3.1.5
Requires-Dist: pandas>=2.2.3
Requires-Dist: polars>=1.12.0
Requires-Dist: pyarrow>=18.0.0
Requires-Dist: sphinx>=8.1.3
Requires-Dist: tox>=4.23.2
Provides-Extra: dev
Requires-Dist: ruff>=0.7.2; extra == "dev"
Requires-Dist: rich>=13.9.4; extra == "dev"
Requires-Dist: pytest>=8.3.3; extra == "dev"
Requires-Dist: tox>=4.18.1; extra == "dev"
